README.md
setup.py
functions/__init__.py
functions/abstract_factory.py
functions/utils.py
miniMinio/FileSystem.py
miniMinio/__init__.py
miniMinio.egg-info/PKG-INFO
miniMinio.egg-info/SOURCES.txt
miniMinio.egg-info/dependency_links.txt
miniMinio.egg-info/requires.txt
miniMinio.egg-info/top_level.txt
test/__init__.py
test/test_functions.py
test/snapshots/__init__.py
test/snapshots/snap_test_functions.py
test/unit/__init__.py
test/unit/test_filesystem.py