Metadata-Version: 2.1
Name: miniMinio
Version: 2.6.0
Summary: Exposing file sharing system
Home-page: https://github.com/pypa/sampleproject
Author: Fruitjeus
Author-email: jeu1993@gmail.com
License: UNKNOWN
Platform: UNKNOWN
Classifier: Programming Language :: Python :: 3
Classifier: License :: OSI Approved :: MIT License
Classifier: Operating System :: OS Independent
Requires-Python: >=3.6.1
